pipefun/Functionals.py
pipefun/Pipable.py
pipefun/__init__.py
pypipe/Functionals.py
pypipe/Pipable.py
pypipe/__init__.py
pipefun-0.0.7.dist-info/LICENSE.txt
pipefun-0.0.7.dist-info/METADATA
pipefun-0.0.7.dist-info/WHEEL
pipefun-0.0.7.dist-info/top_level.txt
pipefun-0.0.7.dist-info/RECORD
