Metadata-Version: 2.1
Name: pipefun
Version: 0.0.7
Summary: A lightweight package that contains pipe operators and functional tools
Home-page: https://github.com/starskyC/pipefun
Author: starskyC
Author-email: cl2004_0123@aliyun.com
License: MIT
Platform: UNKNOWN
Classifier: Programming Language :: Python :: 3
Classifier: License :: OSI Approved :: MIT License
Classifier: Operating System :: OS Independent
Requires-Python: >=3.8
